str2td/__init__.py
str2td/_version.py
str2td/error.py
str2td/generate.py
str2td/grammar.lark
str2td/parser_.py
str2td/py.typed
str2td/str2td_.py
str2td/transformer.py
str2td/segments/__init__.py
str2td/segments/date.py
str2td/segments/robostr.py
str2td/segments/weekday.py
str2td-0.0.5.dist-info/METADATA
str2td-0.0.5.dist-info/WHEEL
str2td-0.0.5.dist-info/RECORD
