Metadata-Version: 2.4
Name: str2td
Version: 0.0.5
Summary: Easily convert from short, human readable, and easy to input strings to timedeltas and datetimes
Project-URL: Documentation, https://xkcd.com/730/
Project-URL: Source (GitHub), https://github.com/anamoyee/str2td
Author: anamoyee
Requires-Python: >=3.12
Requires-Dist: lark>=1.2.2
